[
  {
    "id": 308698,
    "genres": [
      13,
      14
    ],
    "name": "EA Sports FC 25",
    "platforms": [
      6,
      48,
      49,
      130,
      167,
      169
    ],
    "release_dates": [
      618669,
      652118,
      652119,
      652120,
      652121,
      652122,
      652123,
      652124,
      652125,
      652126,
      652129,
      652130
    ],
    "summary": "EA SPORTS FC 25 gives you more ways to win for the club. Team up with friends in your favourite modes with the new 5v5 Rush, and manage your club to victory as FC IQ delivers more tactical control than ever before."
  },
  {
    "id": 309043,
    "genres": [
      13,
      14
    ],
    "name": "EA Sports FC 25: Ultimate Edition",
    "platforms": [
      6,
      48,
      49,
      130,
      167,
      169
    ],
    "release_dates": [
      619412,
      619413,
      619414,
      619415,
      619416,
      619417
    ],
    "summary": "Ultimate Edition includes:\n- EA SPORTS FC 25\n- Football Ultimate Team Player Loan Item\n- Ambassador Loan Item\n- Clubs PlayStyles Slot\n- 250000 Clubs Coins\n- Player Career Personality Points\n- 3 ICONs in Player Career\n- 5-star Coach in Manager Career\n- 5-star Youth Scout in Manager Career\n- Up to 7 Days Early Access\n- 4600 FC Points (3850 FC Points on Nintendo Switch)\n- Player Evolution Slot\n- Early Access Rush Rewards"
  }
]